bodger/conf.py
bodger/scripts.py
bodger/version.py
bodger/bodger/cmdmod.py
bodger/bodger/init.py
bodger-4.2.0.dist-info/LICENSE
bodger-4.2.0.dist-info/METADATA
bodger-4.2.0.dist-info/WHEEL
bodger-4.2.0.dist-info/entry_points.txt
bodger-4.2.0.dist-info/top_level.txt
bodger-4.2.0.dist-info/RECORD
