Metadata-Version: 2.1
Name: bodger
Version: 4.2.0
Summary: UNKNOWN
Home-page: UNKNOWN
Author: 
Author-email: 
License: UNKNOWN
Platform: UNKNOWN
Classifier: Operating System :: OS Independent
Classifier: Programming Language :: Python
Classifier: Programming Language :: Python :: 3.6
Classifier: Programming Language :: Python :: 3.7
Classifier: Programming Language :: Python :: 3.8
Classifier: Development Status :: 5 - Production/Stable
Requires-Python: >=3.6
License-File: LICENSE
Requires-Dist: pop (==14)
Requires-Dist: grainsv2 (==11.6)
Requires-Dist: grains-universal (>=2.1)
Requires-Dist: grains-virt (>=3)
Requires-Dist: idem-bsd (>=4.2) ; "BSD" in sys_platform
Requires-Dist: idem-solaris (>=4.2) ; "sunos" in sys_platform
Requires-Dist: idem-aix (>=4.2) ; os_name == "AIX"
Requires-Dist: idem-posix (>=2.3) ; os_name == "posix"
Requires-Dist: idem-darwin (>=8.2) ; sys_platform == "darwin"
Requires-Dist: idem-linux (>=7.2) ; sys_platform == "linux"
Requires-Dist: idem-windows (>=5.3) ; sys_platform == "win32"
